odoo/addons/sale_order_line_name_get/LICENSE
odoo/addons/sale_order_line_name_get/README.rst
odoo/addons/sale_order_line_name_get/__init__.py
odoo/addons/sale_order_line_name_get/__manifest__.py
odoo/addons/sale_order_line_name_get/images/screen.png
odoo/addons/sale_order_line_name_get/models/__init__.py
odoo/addons/sale_order_line_name_get/models/sale_order_line.py
odoo/addons/sale_order_line_name_get/static/description/icon.png
odoo/addons/sale_order_line_name_get/static/description/index.html
odoo/addons/sale_order_line_name_get/tests/TEST_INSTRUCTIONS.rst
odoo_addon_sale_order_line_name_get-16.0.1.0.0.dist-info/METADATA
odoo_addon_sale_order_line_name_get-16.0.1.0.0.dist-info/WHEEL
odoo_addon_sale_order_line_name_get-16.0.1.0.0.dist-info/top_level.txt
odoo_addon_sale_order_line_name_get-16.0.1.0.0.dist-info/RECORD
